opentelemetry/exporter/prometheus_remote_write/__init__.py
opentelemetry/exporter/prometheus_remote_write/version.py
opentelemetry/exporter/prometheus_remote_write/gen/remote_pb2.py
opentelemetry/exporter/prometheus_remote_write/gen/types_pb2.py
opentelemetry/exporter/prometheus_remote_write/gen/gogoproto/gogo_pb2.py
opentelemetry_exporter_prometheus_remote_write-0.60b1.dist-info/METADATA
opentelemetry_exporter_prometheus_remote_write-0.60b1.dist-info/WHEEL
opentelemetry_exporter_prometheus_remote_write-0.60b1.dist-info/RECORD
