Metadata-Version: 2.4
Name: opentelemetry-exporter-prometheus-remote-write
Version: 0.60b1
Summary: Prometheus Remote Write Metrics Exporter for OpenTelemetry
Project-URL: Homepage, https://github.com/open-telemetry/opentelemetry-python-contrib/tree/main/exporter/opentelemetry-exporter-prometheus-remote-write
Project-URL: Repository, https://github.com/open-telemetry/opentelemetry-python-contrib
Author-email: OpenTelemetry Authors <cncf-opentelemetry-contributors@lists.cncf.io>
License-Expression: Apache-2.0
Classifier: Development Status :: 4 - Beta
Classifier: Intended Audience :: Developers
Classifier: License :: OSI Approved :: Apache Software License
Classifier: Programming Language :: Python
Classifier: Programming Language :: Python :: 3
Classifier: Programming Language :: Python :: 3.9
Classifier: Programming Language :: Python :: 3.10
Classifier: Programming Language :: Python :: 3.11
Classifier: Programming Language :: Python :: 3.12
Classifier: Programming Language :: Python :: 3.13
Requires-Python: >=3.9
Requires-Dist: opentelemetry-api~=1.12
Requires-Dist: opentelemetry-sdk~=1.12
Requires-Dist: protobuf~=5.26
Requires-Dist: python-snappy~=0.6
Requires-Dist: requests~=2.28
